<Document>صالح بن يوسف صالح بن يوسف ميدون ، 11 أكتوبر 1907 - فرانكفورت ، 2 جوان 1961 ، هو أحد أبرز قادة <NERMM>الحركة الوطنية التونسية</NERMM> . تولى الأمانة العامة <NEOPO>للحزب الحر</NEOPO> الدستوري الجديد كما تولى <NEOPG>وزارة العدل</NEOPG> في حكومة محمد شنيق التفاوضية بين 1950 و1952 . عارض سنة <NETD>1955</NETD> الاستقلال الداخلي الذي قبل به بورقيبة مما أدى إلى حدوث صدام بينهما . أدى الخلاف إلى حدوث شرخ في <NEOPO>الحزب الدستوري</NEOPO> وإلى دخول أنصار الفريقين في صراع مفتوح . ورغم حصوله على تأييد جزء كبير من الإطارات الدستورية خسر بن يوسف صراع الزعامة ووقع فصله من الحزب . إختار ابتداءا من جانفي 1956 اللجوء إلى المنفى وتقرب من جمال عبد الناصر . إلا أن إعلان الاستقلال في <NETD>مارس 1956</NETD> <NELGO>والجمهورية في جويلية</NELGO> 1957 وإبتعاده عن البلاد أدى إلى إضعاف موقفه ليقع في النهاية اغتياله في جوان 1961 في <NELGO>ألمانيا</NELGO> .نشأته وبداياتهولد <NEP>بميدون</NEP> بجربة في 11 أكتوبر 1907 . في وسط على قدر كبير من الثراء تعلم مبادئ القراءة والكتابة في <NERTB>كتاب القرية جامع حاضر باش</NERTB> ولما بلغ الثامنة من عمره ارسله جده إلى العاصمة ليتعلم في <NEFGH>المدارس العصرية</NEFGH> فتحصل على الشهادة الابتدائية في <NEFGH>مدرسة نهج</NEFGH> التريبينال ثم التحق بمعهد كارنو وبما انه لم يكن <NERL>للغة العربية</NERL> نصيب هام في ذلك المعهد انتدب له والده أحد شيوخ الزيتونة المتضلعين في اللغة فتكون على يده . وكان في الآن نفسه يتابع الدروس الليلية في <NEFGH>مدرسة العطارين</NEFGH> فنال من تلك <NEFGH>المدرسة المؤهل العربي </NEFGH> ثم نال الديبلوم العالي العربي ومن معهد كارنو الباكلوريا سنة <NETD>1930</NETD> .التحق <NEP>بفرنسا لمواصلة تعليمه</NEP> في السربون فحصل على الاجازة في الحقوق والعلوم السياسية سنة <NETD>1933</NETD> . وعاد إلى <NELGO>تونس</NELGO> في صائفة 1934 ليفتح مكتب محاماة جعله مقرا لنشاطه الوطني والتحق مباشرة بصفوف <NEOPO>  الحزب الحر</NEOPO> الدستوري الجديد واحتل فيه المراتب <NEUO>الأولى</NEUO> فكان يحضر اجتماعات <NEOC>الديوان السياسي</NEOC> والهيئة السياسية دون أن يكون عضوا فيهما .معارضته الاستقلال الداخليكان عام <NETD>1954</NETD> عاماً <NEC>أسود</NEC> بالنسبة للامبراطورية الفرنسية . فقد مني <NEOPM>جيشها</NEOPM> <NEEI>بهزيمة</NEEI> ثقيلة في <NEEI> معركة ديان بيان</NEEI> فو الشهيرة في <NELGO>فيتنام</NELGO> أو <NELGO>الهند</NELGO> <NELGO>الصينية</NELGO> ، كما كانت تسمى في ذلك الوقت . وقد استقبلت الشعوب الراضخة للهيمنة الاستعمارية الفرنسية هذا الأمر بدهشة كبيرة ممزوجة بالأمل ، إذ انه بدا لها أنها قادرة هي أيضا على الانتصار على تلك القوة الغاشمة التي ظلت تنكل بها على مدى عقود طويلة . وفي 18 جوان <NETD>حزيران</NETD> 1954 ، أطاحت <NEOPO>الجمعية الوطنية</NEOPO> الفرنسية حكومة لانيال وكلفت بيار منداس فرانس إجراء مفاوضات لإحلال السلام في <NELGO>الهند</NELGO> <NELGO>الصينية</NELGO> . وقد استقبل بورقيبة الذي كان آنذاك في المنفى هذه التطورات الجديدة بنوع من الانشراح والابتهاج ، إذ انه كان يرتبط بعلاقات ودية برئيس الوزراء الفرنسي الجديد ، وكان يثق في «صدقه ونزاهته» حسب تعبيره . وفي 30 جويلية تموز من العام المذكور ، صادق <NEOC>مجلس الوزراء الفرنسي </NEOC> على مبدأ منح البلاد <NELGO>التونسية</NELGO> الاستقلال الداخلي . وفي اليوم التالي تحول بيار منداس فرانس إلى قرطاج مصحوبا بالماريشال جوان <NELGC>وبالسيد </NELGC> كريستيان فوشي <NEJ>الوزير المكلف</NEJ> بالشؤون التونسية <NELGO>والمغربية</NELGO> والمشهور بموالاته للجنرال ديغول ، ليعلن أمام محمد الأمين باي عن نية <NELGO>فرنسا</NELGO> منح تونس استقلالها الداخلي قائلا : «إن درجة التطور التي بلغها الشعب التونسي والتي يحق لنا أن نبتهج بها ، لا سيّما وقد ساهمنا كثيراً في ذلك ، وكذلك قيمة نخبته اللافتة للنظر ، تبرر قيام ذلك الشعب بإدارة شؤونه بنفسه . وبناء على ذلك فإننا مستعدون لإحالة الممارسة الداخلية للسيادة إلى شخصيات ومؤسسات تونسية» .وبناء على هذا التصريح ، تكونت وزارة كلفت بقيادة المفاوضات وذلك يوم 8 أوت 1954 ، وقد ترأس هذه <NEOPG>الوزارة السيد</NEOPG> الطاهر بن عمار ، وهو أحد أعيان العاصمة ومعروف باعتداله وبمواقفه الوطنية الشجاعة . وقد تمّ ذلك بموافقة من <NELGO>فرنسا</NELGO> ومن <NEOPO>الحزب الحر</NEOPO> الدستوري <NELGO>التونسي </NELGO> الذي كان يقود المعركة من أجل استقلال <NELGO>تونس</NELGO> منذ العشرينات . ومن «شانتيسي» في <NELGO>فرنسا</NELGO> ، حيث كان هناك ، سارع بورقيبة بتأييد المفاوضات بين <NELGO>فرنسا</NELGO> <NELGO>وتونس</NELGO> من أجل الاستقلال الداخلي طالبا من المقاومين المسلحين الذين كانوا يسمون آنذاك بـ «الفلاقة» بالنزول من الجبال ، وتسليم أسلحتهم . وبالرغم من أن اليمين الفرنسي تمكن من إسقاط <NEOPG>حكومة السيد</NEOPG> بيار منداس فرانس متهما إياها بالتخلي عن <NELRD>شمال أفريقيا </NELRD> بعد التفويت في <NELGO>الهند</NELGO> <NELGO>الصينية</NELGO> ، فإن المفاوضات الفرنسية - <NELGO>التونسية</NELGO> تواصلت بفضل السيد ادغار فور ، رئيس <NEOPG>الحكومة الفرنسية الجديد</NEOPG> ، الذي حرص على مقابلة بورقيبة في 21 أفريل <NETD>نيسان</NETD> 1955 ، ممهداً بذلك لإمضاء الاتفاقيات الفرنسية - <NELGO> التونسية </NELGO> في 3 جوان 1955 . وقد نصّت تلك الاتفاقيات على استرجاع <NELGO>الدولة التونسية</NELGO> لجميع صلاحيات سيادتها الداخلية ، غير أنها أبقت <NELGO>لفرنسا </NELGO> امتيازات كبيرة أمنيّة وعسكرية وسياسية . واستبشارا بهذه الاتفاقيات ، خصّ الشعب التونسي <NEI>الزعيم</NEI> <NEP>بورقيبة</NEP> عند عودته إلى تونس يوم فاتح جوان / حزيران من العام المذكور باستقبال جماهيري لم يسبق له مثيل ، إذ حمل على الأعناق مسافات طويلة ، ورافقته الجماهير الهاتفة بحياته من ميناء حلق الوادي حتى بيته بساحة «معقل الزعيم» . اما <NEI>الزعيم</NEI> <NEP>صالح بن يوسف</NEP> الموجود آنذاك <NELGO>بسويسرا</NELGO> والذي كان أميناً عاماً <NEOPO>للحزب الحر</NEOPO> الدستوري ، فقد عبّر عن معارضته التامة لاتفاقيات الاستقلال الداخلي متهما بورقيبة بـ «الخيانة الوطنية» ، وحاثّا المقاومين على مواصلة الكفاح المسلح من أجل الحصول على الاستقلال التام لا بالنسبة لتونس فحسب ، وإنما لجميع <NELGO>البلدان المغاربية</NELGO> . وبالرغم من أن عدة شخصيات وطنية بينها السيد المنجي سليم الذي كان يقود آنذاك المفاوضات الفرنسية - التونسية في <NELGC>باريس</NELGC> ، كانت قد اتصلت <NEI>بالزعيم</NEI> <NEP>صالح بن يوسف</NEP> لإقناعه بضرورة التراجع عن موقفه ذاك ، غير أنه رفض ذلك رفضاً قاطعاً مواصلاً نقده اللاذع لبورقيبة .الصدام مع بورقيبةولا بدّ من الإشارة إلى أن موقف صالح بن يوسف لاقى في البداية تجاوباً عند الكثيرين ، خصوصاً أن الاتفاقيات كانت تنصّ على ضرورة تقيّد <NELGO>تونس</NELGO> <NERRT>بمعاهدة باردو</NERRT> التي تمّ بموجبها دخول الاستعمار إلى البلاد ، كما أنها تمنح <NELGO>فرنسا</NELGO> سلطة الإشراف على الأمن الجوي والبحري ، وتخوّل لها مواصلة نفوذها وسلطتها على المؤسسات الأمنية . وقد صرح بعض <NEOPO>جماعة </NEOPO> الحزب القديم الذي كان يتزعمه <NEI>الشيخ </NEI> <NEP>عبد العزيز الثعالبي</NEP> بأن «الاتفاقيات تمثل مؤامرة استعمارية جديدة» .وداخل <NEOPO>الحزب الحر</NEOPO> الدستوري نفسه ، ارتفعت أصوات للتنديد بالاتفاقيات ، معبرة بذلك عن مساندتها لصالح بن يوسف . وقد زعزع الخلاف بين <NEJ>الزعيمين الكبيرين</NEJ> المجموعات الوطنية الأخرى ، مثل <NEOC>اتحاد النقابات واتحاد</NEOC> الطلبة باثاً في صفوفها الصراعات والانقسامات . وكان واضحاً ، ان البلاد مقبلة على تطورات خطيرة قد تقوّض تلك الفرحة العارمة التي هزّت الشعب <NELGO> التونسي</NELGO> عند إعلان <NELGO>فرنسا</NELGO> عن قبولها منح <NELGO>تونس</NELGO> استقلالها الداخلي .وفي 13 <NETD>سبتمبر</NETD> 1955 ، عاد <NEP>صالح بن يوسف</NEP> إلى <NELGO>تونس</NELGO> ، فخصّ باستقبال جماهيري كبير ، وكان <NEP>بورقيبة</NEP> في مقدمة مستقبليه . وعندما شاهدتهما الجماهير وهما يسيران جنباً إلى جنب ، ازدادت حماساً وفرحاً ، ذلك أنها اعتقدت أن <NEJ>الزعيمين تصالحا</NEJ> وان جميع الخلافات القائمة بينهما قد سويت . وقد ازداد اقتناعها بذلك لما أطلّ الزعيمان من شرفة بيت صالح بن يوسف للرد على تحياتها وهتافاتها . ثم خطب صالح بن يوسف مركزاً على أن الاتفاقيات منقوصة وأنها تمثل خطراً كبيراً على «استقلالنا وحريتنا» . وأجابه بورقيبة بأن هذه الاتفاقيات إيجابية لأنها تخلّص <NELGO>تونس</NELGO> من الإدارة الاستعمارية ، غير أنها لا توقف ولن توقف مسيرة <NELGO>تونس</NELGO> نحو استقلالها التام . وهنا بدا واضحاً للجميع أن كل واحد من <NEJ>الزعيمين متمسك</NEJ> بموقفه وان الخلافات لا تزال قائمة بينهما . وعندئذ انطفأت الفرحة في قلوب الجماهير المتراصة فانسحبت حزينة .وفي يوم 7 أكتوبر تشرين <NEUO>الأول</NEUO> ، ألقى <NEI>الزعيم</NEI> <NEP>صالح بن يوسف</NEP> خطاباً <NELRC>حماسياً</NELRC> أمام <NEFGW>جامع الزيتونة</NEFGW> أعلن فيه من جديد رفضه القاطع لاتفاقيات الاستقلال الداخلي ، محرّضاً على ضرورة مواصلة الكفاح المسلح من أجل الحصول على الاستقلال التام ودعم نضال الشعب <NELGO>الجزائري</NELGO> <NELGO> والمغربي</NELGO> للحصول على استقلالهما . وفي الأيام التالية ، واصل صالح بن يوسف حملته ضد بورقيبة ، <NEUP>محاولاً</NEUP> تأليب الرأي العام ضده ، متهما إياه بالكفر وبأنه «عميل للغرب وعدو للعروبة <NERMR>والإسلام»</NERMR> . ورغم ذلك ، تواصلت <NEUP>المحاولات</NEUP> لإصلاح ذات البين بين الزعيمين ، لكن دون أن يفضي ذلك إلى أية نتيجة تذكر . وفي <NETD>. نوفمبر تشرين</NETD> <NEUO>الثاني</NEUO> 1955 ، عقد <NEOPO>الحزب الحر</NEOPO> الدستوري مؤتمره العام في <NELGC> مدينة صفاقس</NELGC> عاصمة الجنوب <NELGO>التونسي</NELGO> وحصل بورقيبة على تأييد واضح وصريح من قيادة اتحاد النقابات بزعامة الحبيب عاشور وأحمد بن صالح . وفي نهاية المؤتمر المذكور ، اتخذ أنصار بورقيبة قراراً يقضي بطرد صالح بن يوسف من الحزب ، غير أن هذا الأخير سارع بتكوين أمانة عامة رافضاً القرار المذكور . وهكذا باتت البلاد بأسرها على حافة <NEEI>حرب أهلية</NEEI> مدمرة .المنفىفي 28 جانفي كانون <NEUO>الثاني</NEUO> 1956 ، أصدر المنجي سليم الذي كان آنذاك <NEJ>وزيرا للداخلية</NEJ> أمراً باعتقال البعض من أنصار صالح بن يوسف الذي تمكن من أن يتجاوز الحدود متوجها إلى <NELGC>طرابلس</NELGC> ومنها إلى <NELGC>القاهرة</NELGC> . ويبدو أن السلطات <NELGO> التونسية</NELGO> كانت ترغب في خروجه من البلاد ، إذ ان شرطة المرور أوقفت سيارته قرب <NELGC>صفاقس</NELGC> ، غير أن أمراً جاءها من العاصمة يقضي بتركها تمر . وقد التحق <NEP>الطاهر الأسود </NEP> وهو أحد قادة <NERMM>الحركة الوطنية المسلحة</NERMM> بصالح بن يوسف في <NELGC>القاهرة</NELGC> . ومعاً شرعا يخططان للقيام بعمليات عسكرية في <NELGO>تونس </NELGO> لزعزعة النظام . أما أنصار صالح بن يوسف في الداخل فقد دبّروا العديد من العمليات لاغتيال بورقيبة ، غير أن جميعها منيت بالفشل . وقد ردّ النظام <NELGO>التونسي </NELGO> الجديد على هذه العمليات بقسوة شديدة . وفي بيت قديم بـ «صباط الظلام» حذاء الظلام ، بنهج الباشا ، بقلب <NELGC>المدينة العتيقة</NELGC> بالعاصمة ، اخضع العديد من أنصار صالح بن يوسف إلى عمليات تعذيب وحشية قضى البعض منهم بسببها .وقد ازدادت مواقف بورقيبة صلابة عندما قبلت <NELGO>فرنسا</NELGO> منح <NELGO>تونس</NELGO>  استقلالها التام وذلك يوم <NETD>وذلك مارس </NETD> آذار 1956 ، أي عقب مضيّ 9 شهور فقط على امضاء اتفاقيات الاستقلال الداخلي . ومن المؤكد أن وضع المنطقة برمّتها كان عاملاً حاسماً في ذلك ، فقد كانت نيّة <NELGO>فرنسا</NELGO> هي الانفراد <NELGO>بالجزائر</NELGO> ، حيث كانت <NEEI>حرب التحرير الشعبية</NEEI> على أشدها هناك . وكانت تعلم جيدا أنه يصعب عليها مواجهة <NELGO>البلدان المغاربية</NELGO> مجتمعة ، لذا عجلت بمنح <NELGO>المغرب</NELGO> ثم <NELGO>تونس</NELGO> استقلالهما ، مانحة بذلك بورقيبة فرصة تحقيق انتصار سياسي آخر خوّل له شرعية قيادة البلاد .ورغم أن صالح بن يوسف واصل حملته الدعائية ضد بورقيبة انطلاقا من <NELGC>القاهرة</NELGC> ومن عدة أماكن أخرى ، فإن المساعي ظلت مستمرة لعقد مصالحة بينه وبين بورقيبة الذي طلب من السلطات السويسرية مطلع عام <NETD>1961 </NETD> ، ترتيب لقاء بينه وبين خصمه ، وقد وافق صالح بن يوسف على هذا اللقاء ، غير أنه اشترط أن يكون مصحوبا برجال من الأمن السويسري ، الشيء الذي أغضب بورقيبة كثيراً . وفي النهاية تمّ اللقاء بين الزعيمين في أحد الفنادق بزيوريخ بحضور وسيلة زوجة بورقيبة وسكرتيره الخاص علالة العويتي وبشير زرق العيون وهو من <NELCI>جزيرة جربة </NELCI> مثل صالح بن يوسف وبه تربطه علاقة قرابة قوية وتوفيق الترجمان سفير <NELGO>تونس</NELGO> <NELGO>بسويسرا</NELGO> وزوج ابنة وسيلة وكان ذلك في شهر فيفري <NETD> شباط</NETD> 1961 . وحسب المعلومات المتوفرة ، فإن اللقاء لم يعد <NERMT>بطريقة جيدة</NERMT> ، وغلب عليه منذ البداية التشنج والانفعال . فقد مدّ بورقيبة يده لمصافحة صالح بن يوسف غير أن هذا الأخير رفض ذلك . مع ذلك تجاوز بورقيبة هذه الإهانة وخاطب خصمه قائلا : «إنني احترمك كثيراً وأريد أن نتعانق وأن ننتهي من خلافاتنا التي لم يعد لها في الواقع سبب يذكر ، خصوصاً وقد أحرزنا على استقلالنا ، إذن فلنضطلع بهذه المهمة معاً ، أما الباقي فقد كنت أنا على حق ، وكنت أنت مخطئاً ، ذلك لأن الاتفاقيات الفرنسية - <NELGO>التونسية</NELGO> لم تكن خطوة إلى الوراء ، بل كانت خطوة إلى الأمام» . وغاضبا ردّ صالح بن يوسف قائلا : «ليس صحيحاً ، وما زلت اعتبر الاتفاقيات خطوة إلى الوراء ، والاستقلال الصوري الذي تحدثني عنه ليس إلا كارثة على <NELGO>تونس</NELGO> وعلى <NEEI>الثورة الجزائرية</NEEI> التي أعلم أنك تتآمر عليها» . ورد النقاش يحتد بين الزعيمين إلى أن بلغ التوتر درجة قصوى وانقلب اللقاء إلى صياح وتبادل للشتائم والكلمات النابية . وأخيراً اضطرت الشرطة السويسرية للتدخل مخرجة صالح بن يوسف من صالون الفندق .وتؤكد بعض المعلومات ، ان الرئيس بورقيبة أمضى الليلة وهو في حالة استياء وغضب شديدين وانه لم يذق طعم النوم . وقد يكون تفوّه بكلمات شجعت الذين حضروا اللقاء على الشروع في إعداد خطة لتصفية صالح بن يوسف . ويقول بعض من المقربين منه ، إن بورقيبة لم يعط أمراً مباشراً بقتل خصمه ، غير أنه سكت عن ذلك لما قضي الأمر ، بل ومنح أوسمة في احتفال رسمي لمن دبّروا عملية الاغتيال تلك ، وكان ذلك خطأ فادحاً من جانبه ، خصوصا أنه عرف طوال حياته بنبذه للعنف والدم ، عكس العديد من زعماء <NEJ>العالم الثالث</NEJ> الآخرين .الإغتيالوالشيء المؤكد أن من دبروا مؤامرة الاغتيال اختاروا الوقت المناسب لها . ففي مطلع صيف 1961 ، بدأت <NELGO>تونس</NELGO> تعدّ نفسها لخوض <NEEI>معركة الجلاء </NEEI> عن بنزرت ، وبفضل ذلك تمكن بورقيبة من كسب تأييد واسع في الداخل والخارج ، من ذلك تأييد الرئيس <NELGO>المصري</NELGO> جمال عبد الناصر ، الذي كان يحتضن صالح بن يوسف ويدعمه مادياً ومعنوياً . وبما أن الرأي العام <NELGO>التونسي</NELGO> والعربي وحتى العالمي كان منشغلاً بهذه <NEEI>المعركة الجديدة</NEEI> بين <NELGO>تونس </NELGO> <NELGO>وفرنسا</NELGO> ، فإن مدبري مؤامرة اغتيال صالح بن يوسف سارعوا بتنفيذها بعد أن أعدوا خطة محكمة لذلك . ففي 2 جوان 1961 ، غادر <NEI>الزعيم</NEI> <NEP>صالح بن يوسف القاهرة</NEP> مع زوجته متوجها إلى <NELGO>ألمانيا</NELGO> قصد عرض نفسه على طبيب خاص ، وبعد ذلك بحوالي شهرين ، وتحديدا في 11 أغسطس ، كان <NEP> بن يوسف</NEP> يتهيأ للسفر إلى كوناكري لحضور مؤتمر الحزب الديمقراطي الغيني بدعوة من الرئيس أحمد سيكو توري . وفي ذلك اليوم ، اتصل به ابن أخت قريبه ، البشير زرق العيون ، الذي كان يعيش في ألمانيا طالباً منه بإلحاح شديد الالتقاء بخاله «أعني البشير زرق العيون» بهدف إعداد لقاء جديد بينه وبين بورقيبة . وقد وافق الزعيم صالح بن يوسف على ذلك اللقاء الذي اتفق على أن يتم في الساعة السادسة مساء <NETT>في فندق «روي</NETT>ال» <NELGC>بمدينة فرانكفورت</NELGC> الألمانية .وصل <NEI>الزعيم</NEI> <NEP>صالح بن يوسف</NEP> إلى الفندق المذكور في الموعد المحدد ، وكان <NEUO>أول</NEUO> شيء لفت نظره هو أن ليس هناك صالون ، لذا طلب من زوجته أن تنتظره في مقهى مجاور مؤكداً لها أنه لن يتأخر أكثر من نصف ساعة . بعدها صعد إلى غرفة ابن أخت البشير زرق العيون ، وعند وصوله إليها تبين له أن البشير زرق العيون ليس موجوداً ، فلما استفسر عن سبب ذلك ، ردّ عليه ابن الأخت بأن خاله لن يتأخر طويلاً وأنه في الطريق إلى الفندق . فلما جلس <NEI>الزعيم</NEI> <NEP>صالح بن يوسف</NEP> على المقعد ، خرج له قاتلان من غرفة الحمام التي كانت خلفه ليردياه قتيلاً بكاتم الصوت .</Document>